cmip6_data_citation_generator/__init__.py
cmip6_data_citation_generator/_version.py
cmip6_data_citation_generator/cli.py
cmip6_data_citation_generator/drs_handling.py
cmip6_data_citation_generator/io_dcg.py
cmip6_data_citation_generator/upload.py
cmip6_data_citation_generator/utils.py
cmip6_data_citation_generator/validators.py
cmip6_data_citation_generator-0.3.1.dist-info/LICENSE
cmip6_data_citation_generator-0.3.1.dist-info/METADATA
cmip6_data_citation_generator-0.3.1.dist-info/WHEEL
cmip6_data_citation_generator-0.3.1.dist-info/entry_points.txt
cmip6_data_citation_generator-0.3.1.dist-info/top_level.txt
cmip6_data_citation_generator-0.3.1.dist-info/RECORD
