Metadata-Version: 2.1
Name: cmip6-data-citation-generator
Version: 0.3.1
Summary: CMIP6 auxillary tool to generate data citation files from output data files
Home-page: https://github.com/znicholls/CMIP6-json-data-citation-generator
Author: Zebedee Nicholls
Author-email: zebedee.nicholls@climate-energy-college.org
License: 2-Clause BSD License
Keywords: netcdf,python,climate,cmip6
Platform: UNKNOWN
Classifier: Development Status :: 4 - Beta
Classifier: License :: OSI Approved :: BSD License
Classifier: Intended Audience :: Developers
Classifier: Operating System :: OS Independent
Classifier: Programming Language :: Python :: 3.6
Requires-Dist: PyYAML
Requires-Dist: marshmallow (==3.0.0b20)
Requires-Dist: httplib2
Requires-Dist: netcdf-scm
Provides-Extra: deploy
Requires-Dist: twine; extra == 'deploy'
Requires-Dist: setuptools; extra == 'deploy'
Requires-Dist: wheel; extra == 'deploy'
Requires-Dist: flake8; extra == 'deploy'
Requires-Dist: black; extra == 'deploy'
Requires-Dist: versioneer; extra == 'deploy'
Provides-Extra: docs
Requires-Dist: sphinx; extra == 'docs'
Requires-Dist: sphinx-rtd-theme; extra == 'docs'
Provides-Extra: test
Requires-Dist: codecov; extra == 'test'
Requires-Dist: pytest-cov; extra == 'test'
Requires-Dist: pytest; extra == 'test'
